libra/__init__.py
libra/access_path.py
libra/account.py
libra/account_address.py
libra/account_config.py
libra/account_resource.py
libra/bytecode.py
libra/client.mnemonic
libra/client.py
libra/consensus_peers.config.toml
libra/event.py
libra/faucet_key_for_test
libra/get_with_proof.py
libra/hasher.py
libra/identifier.py
libra/json_print.py
libra/key_factory.py
libra/language_storage.py
libra/ledger_info.py
libra/recover.rotate
libra/trusted_peers.py
libra/validator_verifier.py
libra/version.py
libra/violas_resource.py
libra/wallet_library.py
libra/.wallet/module
libra/.wallet/module.rotate
libra/cli/account_cmds.py
libra/cli/color.py
libra/cli/command.py
libra/cli/ledger_cmds.py
libra/cli/main.py
libra/cli/transaction_cmds.py
libra/cli/wallet_cmds.py
libra/proof/__init__.py
libra/proof/account_state_with_proof.py
libra/proof/definition.py
libra/proof/event_with_proof.py
libra/proof/merkle_tree.py
libra/proof/signed_transaction_with_proof.py
libra/proto/__init__.py
libra/proto/access_path_pb2.py
libra/proto/access_path_pb2_grpc.py
libra/proto/account_state_blob_pb2.py
libra/proto/account_state_blob_pb2_grpc.py
libra/proto/admission_control_pb2.py
libra/proto/admission_control_pb2_grpc.py
libra/proto/consensus_pb2.py
libra/proto/consensus_pb2_grpc.py
libra/proto/events_pb2.py
libra/proto/events_pb2_grpc.py
libra/proto/execution_pb2.py
libra/proto/execution_pb2_grpc.py
libra/proto/get_with_proof_pb2.py
libra/proto/get_with_proof_pb2_grpc.py
libra/proto/language_storage_pb2.py
libra/proto/language_storage_pb2_grpc.py
libra/proto/ledger_info_pb2.py
libra/proto/ledger_info_pb2_grpc.py
libra/proto/mempool_pb2.py
libra/proto/mempool_pb2_grpc.py
libra/proto/mempool_status_pb2.py
libra/proto/mempool_status_pb2_grpc.py
libra/proto/network_pb2.py
libra/proto/network_pb2_grpc.py
libra/proto/node_debug_interface_pb2.py
libra/proto/node_debug_interface_pb2_grpc.py
libra/proto/proof_pb2.py
libra/proto/proof_pb2_grpc.py
libra/proto/secret_service_pb2.py
violas_client-0.0.2.dist-info/LICENSE
violas_client-0.0.2.dist-info/METADATA
violas_client-0.0.2.dist-info/WHEEL
violas_client-0.0.2.dist-info/entry_points.txt
violas_client-0.0.2.dist-info/top_level.txt
violas_client-0.0.2.dist-info/RECORD
