Metadata-Version: 2.1
Name: violas-client
Version: 0.0.2
Summary: A CLI inteface Violas client and Python API for Violas blockchain.
Home-page: https://github.com/violas-project/violas-client.git
Author: Xing-Huang
Author-email: hxg@palliums.org
License: UNKNOWN
Platform: UNKNOWN
Classifier: Programming Language :: Python :: 3
Classifier: License :: OSI Approved :: MIT License
Classifier: Operating System :: OS Independent
Requires-Python: >=3.6
Requires-Dist: canoser (>=0.5.2)
Requires-Dist: protobuf
Requires-Dist: grpcio
Requires-Dist: more-itertools
Requires-Dist: PyNaCl
Requires-Dist: pygments
Requires-Dist: requests
Requires-Dist: toml
Requires-Dist: mnemonic
